pyswrd/_version.py
pyswrd/_sword.pypy310-pp73-darwin.so
pyswrd/__init__.py
pyswrd/tests/test_filter.py
pyswrd/tests/test_search.py
pyswrd/tests/__init__.py
pyswrd/tests/test_doctest.py
pyswrd/tests/test_sequences.py
pyswrd/tests/fasta.py
pyswrd/tests/data/uniprot_sprot196.fasta
pyswrd/tests/data/uniprot_sprot12071.fasta
pyswrd/tests/data/__init__.py
pyswrd/tests/data/uniprot_sprot15.fasta
pyswrd/tests/data/O74807.fasta
pyswrd-0.4.2.dist-info/RECORD
pyswrd-0.4.2.dist-info/WHEEL
pyswrd-0.4.2.dist-info/COPYING
pyswrd-0.4.2.dist-info/top_level.txt
pyswrd-0.4.2.dist-info/METADATA
