Metadata-Version: 2.1
Name: pyswrd
Version: 0.4.2
Summary: Cython bindings and Python interface to SWORD, a method for query-database alignment.
Home-page: https://github.com/althonos/pyswrd
Author: Martin Larralde
Author-email: martin.larralde@embl.de
License: MIT
Project-URL: Documentation, https://pyswrd.readthedocs.io/en/stable/
Project-URL: Bug Tracker, https://github.com/althonos/pyswrd/issues
Project-URL: Changelog, https://github.com/althonos/pyswrd/blob/main/CHANGELOG.md
Project-URL: Coverage, https://codecov.io/gh/althonos/pyswrd/
Project-URL: Builds, https://github.com/althonos/pyswrd/actions
Project-URL: PyPI, https://pypi.org/project/pyswrd
Keywords: bioinformatics,sequence,alignment,opal,sword
Platform: any
Classifier: Development Status :: 4 - Beta
Classifier: Intended Audience :: Developers
Classifier: Intended Audience :: Science/Research
Classifier: License :: OSI Approved :: MIT License
Classifier: Operating System :: OS Independent
Classifier: Programming Language :: C
Classifier: Programming Language :: Cython
Classifier: Programming Language :: Python :: 3.6
Classifier: Programming Language :: Python :: 3.7
Classifier: Programming Language :: Python :: 3.8
Classifier: Programming Language :: Python :: 3.9
Classifier: Programming Language :: Python :: 3.10
Classifier: Programming Language :: Python :: 3.11
Classifier: Programming Language :: Python :: 3.12
Classifier: Programming Language :: Python :: Implementation :: CPython
Classifier: Programming Language :: Python :: Implementation :: PyPy
Classifier: Topic :: Scientific/Engineering :: Bio-Informatics
Classifier: Topic :: Scientific/Engineering :: Medical Science Apps.
Classifier: Typing :: Typed
Requires-Python: >=3.5
License-File: COPYING
Requires-Dist: pyopal (~=0.5)
